<PAMDataset>
  <Metadata>
    <MDI key="DataType">Generic</MDI>
  </Metadata>
  <Metadata domain="Esri">
    <MDI key="PyramidResamplingType">NEAREST</MDI>
  </Metadata>
  <PAMRasterBand band="1">
    <Histograms>
      <HistItem>
        <HistMin>-0.5</HistMin>
        <HistMax>12.5</HistMax>
        <BucketCount>13</BucketCount>
        <IncludeOutOfRange>1</IncludeOutOfRange>
        <Approximate>0</Approximate>
        <HistCounts>0|993|213|460|3411|2405|1017|699|0|948|228|732|603</HistCounts>
      </HistItem>
    </Histograms>
    <Metadata>
      <MDI key="RepresentationType">THEMATIC</MDI>
      <MDI key="STATISTICS_COVARIANCES">8.492452624124949</MDI>
      <MDI key="STATISTICS_MAXIMUM">12</MDI>
      <MDI key="STATISTICS_MEAN">5.5993680075156</MDI>
      <MDI key="STATISTICS_MINIMUM">1</MDI>
      <MDI key="STATISTICS_SKIPFACTORX">1</MDI>
      <MDI key="STATISTICS_SKIPFACTORY">1</MDI>
      <MDI key="STATISTICS_STDDEV">2.9141812956858</MDI>
    </Metadata>
  </PAMRasterBand>
</PAMDataset>
